MANIFEST.in
README.rst
setup.cfg
setup.py
PokeapiWrapper.egg-info/PKG-INFO
PokeapiWrapper.egg-info/SOURCES.txt
PokeapiWrapper.egg-info/dependency_links.txt
PokeapiWrapper.egg-info/requires.txt
PokeapiWrapper.egg-info/top_level.txt
pokeapi/__init__.py
pokeapi/pokemon.py
pokeapi/test.py