Metadata-Version: 1.0
Name: PokeapiWrapper
Version: 0.9
Summary: This is a Pokeapi wrapper
Home-page: https://github.com/SocketPhys/Pokeapi-Wrapper
Author: Adithya Mohan
Author-email: Socketphys@gmail.com
License: MIT
Keywords: pokeapi wrapper
Platform: UNKNOWN
